MANIFEST.in
README.txt
setup.py
PyCodeigniter.egg-info/PKG-INFO
PyCodeigniter.egg-info/SOURCES.txt
PyCodeigniter.egg-info/dependency_links.txt
PyCodeigniter.egg-info/requires.txt
PyCodeigniter.egg-info/top_level.txt
codeigniter/__init__.py
codeigniter/application/__init__.py
codeigniter/application/config/__init__.py
codeigniter/application/config/config.py
codeigniter/application/controllers/Index.py
codeigniter/application/controllers/__init__.py
codeigniter/application/helpers/Crawl.py
codeigniter/application/helpers/DictUtil.py
codeigniter/application/helpers/__init__.py
codeigniter/application/library/__init__.py
codeigniter/application/models/IndexModel.py
codeigniter/application/models/__init__.py
codeigniter/application/views/__init__.py
codeigniter/system/__init__.py
codeigniter/system/core/CI_Application.py
codeigniter/system/core/CI_Cache.py
codeigniter/system/core/CI_Cookie.py
codeigniter/system/core/CI_Cron.py
codeigniter/system/core/CI_DB.py
codeigniter/system/core/CI_DBActiveRec.py
codeigniter/system/core/CI_Hook.py
codeigniter/system/core/CI_Input.py
codeigniter/system/core/CI_Loader.py
codeigniter/system/core/CI_Logger.py
codeigniter/system/core/CI_Mail.py
codeigniter/system/core/CI_Memcache.py
codeigniter/system/core/CI_Redis.py
codeigniter/system/core/CI_Request.py
codeigniter/system/core/CI_Response.py
codeigniter/system/core/CI_Router.py
codeigniter/system/core/CI_Session.py
codeigniter/system/core/CI_Static.py
codeigniter/system/core/CI_Template.py
codeigniter/system/core/CI_Util.py
codeigniter/system/core/CI_Zookeeper.py
codeigniter/system/core/__init__.py
test/test.py