Metadata-Version: 1.0
Name: PyCodeigniter
Version: 0.3.3
Summary: Codeigniter(PHP) implement by python
Home-page: https://github.com/sjqzhang/PyCodeigniter
Author: s_jqzhang
Author-email: s_jqzhang@163.com
License: GPL
Platform: UNKNOWN
